ado_asana_sync/__init__.py
ado_asana_sync/database/__init__.py
ado_asana_sync/database/database.py
ado_asana_sync/sync/__init__.py
ado_asana_sync/sync/__main__.py
ado_asana_sync/sync/app.py
ado_asana_sync/sync/asana.py
ado_asana_sync/sync/pull_request_item.py
ado_asana_sync/sync/pull_request_sync.py
ado_asana_sync/sync/sync.py
ado_asana_sync/sync/task_item.py
ado_asana_sync/sync/utils.py
ado_asana_sync/utils/__init__.py
ado_asana_sync/utils/date.py
ado_asana_sync/utils/logging_tracing.py
ado_asana_sync/utils/utils.py
ado_asana_sync-1.24.8.dist-info/METADATA
ado_asana_sync-1.24.8.dist-info/WHEEL
ado_asana_sync-1.24.8.dist-info/entry_points.txt
ado_asana_sync-1.24.8.dist-info/licenses/LICENSE
ado_asana_sync-1.24.8.dist-info/RECORD
