Metadata-Version: 2.4
Name: ado-asana-sync
Version: 1.24.8
Summary: Tool to sync work items and pull requests from Azure DevOps to Asana
Author-email: Dan Anstis <dan@bsod.co.nz>
License: MIT
License-File: LICENSE
Requires-Python: >=3.13
Requires-Dist: asana>=5.0.3
Requires-Dist: azure-devops>=7.1.0b3
Requires-Dist: azure-monitor-opentelemetry>=1.0.0
